templatree/__init__.py
templatree/cli.py
templatree/generator.py
templatree/templates/main.py
templatree/templates/static/index.html
templatree-0.1.0.dist-info/licenses/LICENSE
templatree-0.1.0.dist-info/METADATA
templatree-0.1.0.dist-info/WHEEL
templatree-0.1.0.dist-info/entry_points.txt
templatree-0.1.0.dist-info/top_level.txt
templatree-0.1.0.dist-info/RECORD
