Metadata-Version: 2.4
Name: templatree
Version: 0.1.0
Summary: Templatree directory and file structure with predefined templates.
Author: Önder Ertan
Author-email: onderertan@protonmail.com
License: MIT
Classifier: Programming Language :: Python :: 3
Requires-Python: >=3.6
License-File: LICENSE
Dynamic: author
Dynamic: author-email
Dynamic: classifier
Dynamic: description
Dynamic: description-content-type
Dynamic: license
Dynamic: license-file
Dynamic: requires-python
Dynamic: summary
